enahodata/__init__.py
enahodata/enahodata.py
enahodata-0.0.3.dist-info/LICENSE
enahodata-0.0.3.dist-info/METADATA
enahodata-0.0.3.dist-info/WHEEL
enahodata-0.0.3.dist-info/top_level.txt
enahodata-0.0.3.dist-info/RECORD
