Metadata-Version: 2.1
Name: enahodata
Version: 0.0.3
Summary: Library that automates the download of the modules of the National Household Survey (ENAHO in spanish) conducted by the National Institute of Statistics and Informatics of Peru each year.
Home-page: https://github.com/MaykolMedrano/enahodata2
Author: Maykol Medrano Cahuana & Jelsin Stalin Palomino Huaytapuma
Author-email: maykolmedrano35@gmail.com & jstpalomino@hotmail.com
License: MIT
Keywords: Perú,Peru,inei,enaho,microdatos
Classifier: Programming Language :: Python
Classifier: Operating System :: Microsoft
Classifier: Intended Audience :: Education
License-File: LICENSE
Requires-Dist: requests
Requires-Dist: tqdm
